aludel/__init__.py
aludel/database.py
aludel/service.py
aludel/tests/__init__.py
aludel/tests/doubles.py
aludel/tests/test_database.py
aludel/tests/test_doubles.py
aludel/tests/test_service.py
aludel-0.3.0.dist-info/DESCRIPTION.rst
aludel-0.3.0.dist-info/METADATA
aludel-0.3.0.dist-info/pydist.json
aludel-0.3.0.dist-info/RECORD
aludel-0.3.0.dist-info/top_level.txt
aludel-0.3.0.dist-info/WHEEL
