Metadata-Version: 2.0
Name: aludel
Version: 0.3.0
Summary: A framework for RESTful services using Klein and Alchimia.
Home-page: https://github.com/praekelt/aludel
Author: Praekelt Foundation
Author-email: dev@praekeltfoundation.org
License: MIT
Platform: UNKNOWN
Requires-Dist: Twisted
Requires-Dist: klein
Requires-Dist: sqlalchemy
Requires-Dist: alchimia (>=0.4)
